fastapi_libkit/__init__.py
fastapi_libkit/exceptions.py
fastapi_libkit/permissions.py
fastapi_libkit/responses.py
fastapi_libkit/schemas.py
fastapi_libkit-0.1.3.dist-info/LICENSE
fastapi_libkit-0.1.3.dist-info/METADATA
fastapi_libkit-0.1.3.dist-info/WHEEL
fastapi_libkit-0.1.3.dist-info/RECORD
